collective.polls-1.8.1-py2.7-nspkg.pth
collective/polls/__init__.py
collective/polls/config.py
collective/polls/configure.zcml
collective/polls/logger.py
collective/polls/polls.py
collective/polls/profiles.zcml
collective/polls/setuphandlers.py
collective/polls/subscribers.py
collective/polls/testing.py
collective/polls/Extensions/Install.py
collective/polls/Extensions/__init__.py
collective/polls/browser/__init__.py
collective/polls/browser/configure.zcml
collective/polls/browser/update_poll.py
collective/polls/browser/templates/poll_macros.pt
collective/polls/browser/templates/update_poll.pt
collective/polls/content/__init__.py
collective/polls/content/poll.py
collective/polls/content/models/poll.xml
collective/polls/content/poll_templates/view.pt
collective/polls/locales/collective.polls.pot
collective/polls/locales/manual.pot
collective/polls/locales/plone.pot
collective/polls/locales/cs/LC_MESSAGES/collective.polls.po
collective/polls/locales/cs/LC_MESSAGES/plone.po
collective/polls/locales/de/LC_MESSAGES/collective.polls.po
collective/polls/locales/de/LC_MESSAGES/plone.po
collective/polls/locales/es/LC_MESSAGES/collective.polls.po
collective/polls/locales/es/LC_MESSAGES/plone.po
collective/polls/locales/fr/LC_MESSAGES/collective.polls.po
collective/polls/locales/fr/LC_MESSAGES/plone.po
collective/polls/locales/nl/LC_MESSAGES/collective.polls.po
collective/polls/locales/nl/LC_MESSAGES/plone.po
collective/polls/locales/pt_BR/LC_MESSAGES/collective.polls.po
collective/polls/locales/pt_BR/LC_MESSAGES/plone.po
collective/polls/portlet/__init__.py
collective/polls/portlet/configure.zcml
collective/polls/portlet/voteportlet.pt
collective/polls/portlet/voteportlet.py
collective/polls/profiles/default/cssregistry.xml
collective/polls/profiles/default/jsregistry.xml
collective/polls/profiles/default/metadata.xml
collective/polls/profiles/default/portlets.xml
collective/polls/profiles/default/registry.xml
collective.polls-1.8.1.dist-info/DESCRIPTION.rst
collective.polls-1.8.1.dist-info/METADATA
collective.polls-1.8.1.dist-info/RECORD
collective.polls-1.8.1.dist-info/WHEEL
collective.polls-1.8.1.dist-info/entry_points.txt
collective.polls-1.8.1.dist-info/metadata.json
collective.polls-1.8.1.dist-info/namespace_packages.txt
collective.polls-1.8.1.dist-info/top_level.txt
