Metadata-Version: 2.0
Name: collective.polls
Version: 1.8.1
Summary: A content type, workflow, and portlet for conducting online polls, for anonymous and logged-in users.
Home-page: https://github.com/collective/collective.polls
Author: Franco Pellegrini
Author-email: frapell@ravvit.net
License: UNKNOWN
Keywords: plone dexterity polls
Platform: UNKNOWN
Classifier: Development Status :: 5 - Production/Stable
Classifier: Environment :: Web Environment
Classifier: Framework :: Plone
Classifier: Framework :: Plone :: 4.2
Classifier: Framework :: Plone :: 4.3
Classifier: Intended Audience :: End Users/Desktop
Classifier: Intended Audience :: System Administrators
Classifier: License :: OSI Approved :: GNU General Public License v2 (GPLv2)
Classifier: Operating System :: OS Independent
Classifier: Programming Language :: JavaScript
Classifier: Programming Language :: Python
Classifier: Programming Language :: Python :: 2.7
Classifier: Topic :: Office/Business :: News/Diary
Classifier: Topic :: Software Development :: Libraries :: Python Modules
Requires-Dist: AccessControl
Requires-Dist: Products.CMFCore
Requires-Dist: Products.CMFPlone (>=4.2)
Requires-Dist: Products.GenericSetup
Requires-Dist: collective.z3cform.widgets (>=1.0b3)
Requires-Dist: five.grok
Requires-Dist: plone.api
Requires-Dist: plone.app.dexterity[grok,relations]
Requires-Dist: plone.app.portlets
Requires-Dist: plone.app.referenceablebehavior
Requires-Dist: plone.directives.dexterity
Requires-Dist: plone.memoize
Requires-Dist: plone.portlets
Requires-Dist: plone.uuid
Requires-Dist: setuptools
Requires-Dist: zope.component
Requires-Dist: zope.i18nmessageid
Requires-Dist: zope.interface
Requires-Dist: zope.schema
Provides-Extra: test
Requires-Dist: collective.cover; extra == 'test'
Requires-Dist: mock; extra == 'test'
Requires-Dist: plone.app.robotframework; extra == 'test'
Requires-Dist: plone.app.testing[robot] (>=4.2.2); extra == 'test'
Requires-Dist: plone.dexterity; extra == 'test'
Requires-Dist: plone.testing; extra == 'test'
Requires-Dist: robotsuite; extra == 'test'
